{
  "vat": 32311482,
  "name": "AAKA EJENDOMME ApS",
  "address": "Bjerreby Møllevej 13A",
  "zipcode": "5700",
  "city": "Svendborg",
  "cityname": "Tåsinge",
  "protected": true,
  "phone": "40157926",
  "email": null,
  "fax": null,
  "startdate": "09/02 - 2011",
  "enddate": "23/01 - 2019",
  "employees": null,
  "addressco": "Kurt Andersen",
  "industrycode": 682040,
  "industrydesc": "Udlejning af erhvervsejendomme",
  "companycode": 80,
  "companydesc": "Anpartsselskab",
  "creditstartdate": null,
  "creditbankrupt": false,
  "creditstatus": null,
  "owners": null,
  "productionunits": [
    {
      "pno": 1016642734,
      "main": true,
      "name": "AAKA EJENDOMME ApS",
      "address": "Bjerreby Møllevej 13A",
      "zipcode": "5700",
      "city": "Svendborg",
      "cityname": "Tåsinge",
      "protected": false,
      "phone": null,
      "email": null,
      "fax": null,
      "startdate": "09/02 - 2011",
      "enddate": "23/01 - 2019",
      "employees": null,
      "addressco": "Kurt Andersen",
      "industrycode": 682040,
      "industrydesc": "Udlejning af erhvervsejendomme"
    }
  ],
  "t": 100,
  "version": 6
}
