{
  "took": 3,
  "timed_out": false,
  "_shards": {
    "total": 3,
    "successful": 3,
    "skipped": 0,
    "failed": 0
  },
  "hits": {
    "total": 9,
    "max_score": 1,
    "hits": [
      {
        "_index": "indberetninger-20180424",
        "_type": "_doc",
        "_id": "urn:ofk:oid:5383514",
        "_score": 1,
        "_source": {
          "indlaesningsId": null,
          "sagsNummer": "X15-AC-73-QR",
          "regnskab": {
            "regnskabsperiode": {
              "slutDato": "2014-12-31",
              "startDato": "2014-01-01"
            }
          },
          "sidstOpdateret": "2015-05-31T15:28:26.394Z",
          "cvrNummer": 32559506,
          "dokumenter": [
            {
              "dokumentType": "AARSRAPPORT",
              "dokumentMimeType": "application/xhtml+xml",
              "dokumentUrl": "http://regnskaber.virk.dk/60595523/ZG9rdW1lbnRsYWdlcjovLzAzLzc1L2ViL2ZhLzk1L2RjYWYtNGVhMy05NWQzLWYyNTc3OTE5Yjg2Nw.xhtml"
            },
            {
              "dokumentType": "AARSRAPPORT",
              "dokumentMimeType": "application/xml",
              "dokumentUrl": "http://regnskaber.virk.dk/60595523/ZG9rdW1lbnRsYWdlcjovLzAzLzY2LzkzLzlhL2E0LzBlYjctNDU4Yi04OGI1LTZlNjY2YTVjNGFkOA.xml"
            },
            {
              "dokumentType": "AARSRAPPORT",
              "dokumentMimeType": "application/pdf",
              "dokumentUrl": "http://regnskaber.virk.dk/60595523/ZG9rdW1lbnRsYWdlcjovLzAzL2VlLzc3L2NmLzhjLzdhMzUtNDY4My05MTM2LTc1NTgzYTFhZWQ3NA.pdf"
            }
          ],
          "regNummer": null,
          "indlaesningsTidspunkt": "2018-03-31T00:39:55.181Z",
          "offentliggoerelsesTidspunkt": "2015-05-31T15:28:26.351Z",
          "omgoerelse": false,
          "offentliggoerelsestype": "regnskab"
        }
      },
      {
        "_index": "indberetninger-20180424",
        "_type": "_doc",
        "_id": "urn:ofk:oid:22429307",
        "_score": 1,
        "_source": {
          "indlaesningsId": null,
          "sagsNummer": "X16-AW-64-EK",
          "regnskab": {
            "regnskabsperiode": {
              "slutDato": "2015-12-31",
              "startDato": "2015-01-01"
            }
          },
          "sidstOpdateret": "2016-05-24T14:12:52.169Z",
          "cvrNummer": 32559506,
          "dokumenter": [
            {
              "dokumentType": "AARSRAPPORT",
              "dokumentMimeType": "application/xml",
              "dokumentUrl": "http://regnskaber.virk.dk/60595523/ZG9rdW1lbnRsYWdlcjovLzAzLzFiL2Q1Lzg3Lzc3LzFhNTgtNDg1Ni05MWI4LWM3NGZmNWE5OWI4Mg.xml"
            },
            {
              "dokumentType": "AARSRAPPORT",
              "dokumentMimeType": "application/xhtml+xml",
              "dokumentUrl": "http://regnskaber.virk.dk/60595523/ZG9rdW1lbnRsYWdlcjovLzAzLzM2LzE5LzQyL2E0LzM0ZDgtNGU3OC1hODgwLWFkNjJiNzcxMzUwNQ.xhtml"
            },
            {
              "dokumentType": "AARSRAPPORT",
              "dokumentMimeType": "application/pdf",
              "dokumentUrl": "http://regnskaber.virk.dk/60595523/ZG9rdW1lbnRsYWdlcjovLzAzLzUzL2U3L2I3LzlhLzgxMjQtNGExNC04MGM1LTg5NWFhYzM0MTdjOA.pdf"
            }
          ],
          "regNummer": null,
          "indlaesningsTidspunkt": "2018-03-29T01:46:06.270Z",
          "offentliggoerelsesTidspunkt": "2016-05-24T14:12:51.868Z",
          "omgoerelse": false,
          "offentliggoerelsestype": "regnskab"
        }
      },
      {
        "_index": "indberetninger-20180424",
        "_type": "_doc",
        "_id": "urn:ofk:oid:24936161",
        "_score": 1,
        "_source": {
          "indlaesningsId": null,
          "sagsNummer": "X18-AA-74-FH",
          "regnskab": {
            "regnskabsperiode": {
              "slutDato": "2017-12-31",
              "startDato": "2017-01-01"
            }
          },
          "sidstOpdateret": "2018-01-10T11:38:52.680Z",
          "cvrNummer": 32559506,
          "dokumenter": [
            {
              "dokumentType": "AARSRAPPORT",
              "dokumentMimeType": "application/xml",
              "dokumentUrl": "http://regnskaber.virk.dk/60595523/ZG9rdW1lbnRsYWdlcjovLzAzLzc0L2FkL2E3L2QwL2MzZjQtNDZiNy1hYzE5LWYzNmNmZDM0YmQ1YQ.xml"
            },
            {
              "dokumentType": "AARSRAPPORT",
              "dokumentMimeType": "application/pdf",
              "dokumentUrl": "http://regnskaber.virk.dk/60595523/ZG9rdW1lbnRsYWdlcjovLzAzLzg2LzViLzVjLzI1LzgyYzMtNGFlYi1hZWFiLWU4MzdlYjUyY2Q4NQ.pdf"
            },
            {
              "dokumentType": "AARSRAPPORT",
              "dokumentMimeType": "application/xhtml+xml",
              "dokumentUrl": "http://regnskaber.virk.dk/60595523/ZG9rdW1lbnRsYWdlcjovLzAzLzU1LzhjL2FhL2ZiLzA1N2UtNDg2My04MTQ3LTE1YTdiYmM2MjljZQ.xhtml"
            }
          ],
          "regNummer": null,
          "indlaesningsTidspunkt": "2018-04-03T14:45:34.862Z",
          "offentliggoerelsesTidspunkt": "2018-01-10T11:38:52.475Z",
          "omgoerelse": false,
          "offentliggoerelsestype": "regnskab"
        }
      },
      {
        "_index": "indberetninger-20180424",
        "_type": "_doc",
        "_id": "urn:ofk:oid:23727791",
        "_score": 1,
        "_source": {
          "indlaesningsId": null,
          "sagsNummer": "X17-AG-28-FX",
          "regnskab": {
            "regnskabsperiode": {
              "slutDato": "2016-12-31",
              "startDato": "2016-01-01"
            }
          },
          "sidstOpdateret": "2017-04-18T11:04:04.810Z",
          "cvrNummer": 32559506,
          "dokumenter": [
            {
              "dokumentType": "AARSRAPPORT",
              "dokumentMimeType": "application/xml",
              "dokumentUrl": "http://regnskaber.virk.dk/60595523/ZG9rdW1lbnRsYWdlcjovLzAzLzc5LzNiLzBjLzQxLzgyOTYtNDE0NS04NTM1LTRhZjk5ZWIwNTZmZQ.xml"
            },
            {
              "dokumentType": "AARSRAPPORT",
              "dokumentMimeType": "application/xhtml+xml",
              "dokumentUrl": "http://regnskaber.virk.dk/60595523/ZG9rdW1lbnRsYWdlcjovLzAzLzA2LzBjLzZiLzc5L2Q4MDItNGY4ZS04ZTc5LTk3MTA4ODkwZjQ3Ng.xhtml"
            },
            {
              "dokumentType": "GENERALFORSAMLINGSPROTOKOLLAT",
              "dokumentMimeType": "application/pdf",
              "dokumentUrl": "http://regnskaber.virk.dk/60595523/ZG9rdW1lbnRsYWdlcjovLzAzL2VjLzY1L2VhLzRhLzFjNDUtNGJmMS05NWI3LTE5MjBmYzdkMDA5YQ.pdf"
            },
            {
              "dokumentType": "AARSRAPPORT",
              "dokumentMimeType": "application/pdf",
              "dokumentUrl": "http://regnskaber.virk.dk/60595523/ZG9rdW1lbnRsYWdlcjovLzAzLzk5LzdjLzk4LzRiLzNmYjktNGExZi1hYjk5LTg3NDQyZmJjNTVlMg.pdf"
            }
          ],
          "regNummer": null,
          "indlaesningsTidspunkt": "2018-03-27T13:29:46.726Z",
          "offentliggoerelsesTidspunkt": "2017-04-18T11:04:04.497Z",
          "omgoerelse": false,
          "offentliggoerelsestype": "regnskab"
        }
      },
      {
        "_index": "indberetninger-20180424",
        "_type": "_doc",
        "_id": "urn:ofk:oid:20473719",
        "_score": 1,
        "_source": {
          "indlaesningsId": null,
          "sagsNummer": "13-107.488",
          "regnskab": {
            "regnskabsperiode": {
              "slutDato": "2012-12-31",
              "startDato": "2012-01-01"
            }
          },
          "sidstOpdateret": "2013-06-20T22:00:00.000Z",
          "cvrNummer": 32559506,
          "dokumenter": [
            {
              "dokumentType": "AARSRAPPORT",
              "dokumentMimeType": "application/xml",
              "dokumentUrl": "http://regnskaber.virk.dk/60595523/Y3ZyLmRrOi8veGJybHMvWC1GRkI4Q0E1NC0yMDEzMDYyMF8xMzE5MjFfNjc2.xml"
            },
            {
              "dokumentType": "AARSRAPPORT",
              "dokumentMimeType": "application/pdf",
              "dokumentUrl": "http://regnskaber.virk.dk/60595523/Y3ZyLmRrOi8vcGRmcy8zMjU1OTUwNjtBcFM0NjQxNDk7MjAxMjAxMDE7MjAxMjEyMzE7UjtS.pdf"
            }
          ],
          "regNummer": null,
          "indlaesningsTidspunkt": "2018-04-02T06:06:52.781Z",
          "offentliggoerelsesTidspunkt": "2013-06-20T22:00:00.000Z",
          "omgoerelse": false,
          "offentliggoerelsestype": "regnskab"
        }
      },
      {
        "_index": "indberetninger-20180424",
        "_type": "_doc",
        "_id": "urn:ofk:oid:20473725",
        "_score": 1,
        "_source": {
          "indlaesningsId": null,
          "sagsNummer": "14-107.581",
          "regnskab": {
            "regnskabsperiode": {
              "slutDato": "2013-12-31",
              "startDato": "2013-01-01"
            }
          },
          "sidstOpdateret": "2014-06-19T22:00:00.000Z",
          "cvrNummer": 32559506,
          "dokumenter": [
            {
              "dokumentType": "AARSRAPPORT",
              "dokumentMimeType": "application/xml",
              "dokumentUrl": "http://regnskaber.virk.dk/60595523/Y3ZyLmRrOi8veGJybHMvWC1GRkI4Q0E1NC0yMDE0MDYxOV8xNDQwNTVfMDY0.xml"
            },
            {
              "dokumentType": "AARSRAPPORT",
              "dokumentMimeType": "application/pdf",
              "dokumentUrl": "http://regnskaber.virk.dk/60595523/Y3ZyLmRrOi8vcGRmcy8zMjU1OTUwNjtBcFM0NjQxNDk7MjAxMzAxMDE7MjAxMzEyMzE7UjtS.pdf"
            }
          ],
          "regNummer": null,
          "indlaesningsTidspunkt": "2018-04-01T07:34:21.227Z",
          "offentliggoerelsesTidspunkt": "2014-06-19T22:00:00.000Z",
          "omgoerelse": false,
          "offentliggoerelsestype": "regnskab"
        }
      },
      {
        "_index": "indberetninger-20180424",
        "_type": "_doc",
        "_id": "urn:ofk:oid:20473716",
        "_score": 1,
        "_source": {
          "indlaesningsId": null,
          "sagsNummer": "12-113.802",
          "regnskab": {
            "regnskabsperiode": {
              "slutDato": "2011-12-31",
              "startDato": "2011-01-01"
            }
          },
          "sidstOpdateret": "2012-04-15T22:00:00.000Z",
          "cvrNummer": 32559506,
          "dokumenter": [
            {
              "dokumentType": "AARSRAPPORT",
              "dokumentMimeType": "image/tiff",
              "dokumentUrl": "http://regnskaber.virk.dk/60595523/Y3ZyLmRrOi8vcGRmcy8zMjU1OTUwNjtBcFM0NjQxNDk7MjAxMTAxMDE7MjAxMTEyMzE7UjtS.tif"
            }
          ],
          "regNummer": null,
          "indlaesningsTidspunkt": "2018-04-02T03:33:18.292Z",
          "offentliggoerelsesTidspunkt": "2012-04-15T22:00:00.000Z",
          "omgoerelse": false,
          "offentliggoerelsestype": "regnskab"
        }
      },
      {
        "_index": "indberetninger-20180424",
        "_type": "_doc",
        "_id": "urn:ofk:oid:20473712",
        "_score": 1,
        "_source": {
          "indlaesningsId": null,
          "sagsNummer": "11-7.744",
          "regnskab": {
            "regnskabsperiode": {
              "slutDato": "2010-12-31",
              "startDato": "2009-10-30"
            }
          },
          "sidstOpdateret": "2011-05-29T22:00:00.000Z",
          "cvrNummer": 32559506,
          "dokumenter": [
            {
              "dokumentType": "AARSRAPPORT",
              "dokumentMimeType": "image/tiff",
              "dokumentUrl": "http://regnskaber.virk.dk/60595523/Y3ZyLmRrOi8vcGRmcy8zMjU1OTUwNjtBcFM0NjQxNDk7MjAwOTEwMzA7MjAxMDEyMzE7UjtS.tif"
            }
          ],
          "regNummer": null,
          "indlaesningsTidspunkt": "2018-04-03T03:16:19.195Z",
          "offentliggoerelsesTidspunkt": "2011-05-29T22:00:00.000Z",
          "omgoerelse": false,
          "offentliggoerelsestype": "regnskab"
        }
      },
      {
        "_index": "indberetninger-20180424",
        "_type": "_doc",
        "_id": "urn:ofk:oid:27121138",
        "_score": 1,
        "_source": {
          "cvrNummer": 32559506,
          "regNummer": null,
          "omgoerelse": false,
          "sagsNummer": "X19-BD-02-XP",
          "offentliggoerelsestype": "regnskab",
          "regnskab": {
            "regnskabsperiode": {
              "startDato": "2018-01-01",
              "slutDato": "2018-12-31"
            }
          },
          "offentliggoerelsesTidspunkt": "2019-05-11T09:56:44.652Z",
          "indlaesningsTidspunkt": "2019-05-11T09:57:37.706Z",
          "sidstOpdateret": "2019-05-11T09:56:45.043Z",
          "dokumenter": [
            {
              "dokumentUrl": "http://regnskaber.virk.dk/60595523/ZG9rdW1lbnRsYWdlcjovLzAzLzZkLzdlLzM0LzU5L2IxMzUtNDRlZC05MTk5LTg5ZTJhM2U4OGJiZQ.xml",
              "dokumentMimeType": "application/xml",
              "dokumentType": "AARSRAPPORT"
            },
            {
              "dokumentUrl": "http://regnskaber.virk.dk/60595523/ZG9rdW1lbnRsYWdlcjovLzAzLzkyL2I2LzRiLzU4L2I4ZmEtNDE0Yy1hZjFmLWU2OWQ4MWI1OGUzZA.xhtml",
              "dokumentMimeType": "application/xhtml+xml",
              "dokumentType": "AARSRAPPORT"
            },
            {
              "dokumentUrl": "http://regnskaber.virk.dk/60595523/ZG9rdW1lbnRsYWdlcjovLzAzL2E3L2I1LzNjLzQyLzU0Y2ItNGNmYy1hYzYzLTI2NGVlY2RiZWUyYg.pdf",
              "dokumentMimeType": "application/pdf",
              "dokumentType": "AARSRAPPORT"
            }
          ],
          "indlaesningsId": "AWqmUs2RRYGX6_YTHmE_"
        }
      }
    ]
  }
}
