{
  "took": 2,
  "timed_out": false,
  "_shards": {
    "total": 3,
    "successful": 3,
    "skipped": 0,
    "failed": 0
  },
  "hits": {
    "total": 5,
    "max_score": 1,
    "hits": [
      {
        "_index": "indberetninger-20180424",
        "_type": "_doc",
        "_id": "urn:ofk:oid:24226969",
        "_score": 1,
        "_source": {
          "indlaesningsId": null,
          "sagsNummer": "X17-AN-30-FY",
          "regnskab": {
            "regnskabsperiode": {
              "slutDato": "2016-12-31",
              "startDato": "2016-01-01"
            }
          },
          "sidstOpdateret": "2017-06-16T14:18:06.242Z",
          "cvrNummer": 35250824,
          "dokumenter": [
            {
              "dokumentType": "AARSRAPPORT",
              "dokumentMimeType": "application/xml",
              "dokumentUrl": "http://regnskaber.virk.dk/42805253/ZG9rdW1lbnRsYWdlcjovLzAzLzM4L2M2LzIyL2FmLzcyMGMtNDg4Mi04YWJlLTgzOTYwYTI0MWMyZQ.xml"
            },
            {
              "dokumentType": "AARSRAPPORT",
              "dokumentMimeType": "application/pdf",
              "dokumentUrl": "http://regnskaber.virk.dk/42805253/ZG9rdW1lbnRsYWdlcjovLzAzL2ZjLzNkLzdmLzdhLzViZTMtNDMzZS04ZmQzLTA0NGMwYzNkMGM2Mg.pdf"
            }
          ],
          "regNummer": null,
          "indlaesningsTidspunkt": "2018-03-29T12:47:34.721Z",
          "offentliggoerelsesTidspunkt": "2017-06-16T14:18:05.869Z",
          "omgoerelse": false,
          "offentliggoerelsestype": "regnskab"
        }
      },
      {
        "_index": "indberetninger-20180424",
        "_type": "_doc",
        "_id": "urn:ofk:oid:22727279",
        "_score": 1,
        "_source": {
          "indlaesningsId": null,
          "sagsNummer": "X16-AZ-87-NX",
          "regnskab": {
            "regnskabsperiode": {
              "slutDato": "2015-12-31",
              "startDato": "2015-01-01"
            }
          },
          "sidstOpdateret": "2016-06-17T14:14:20.626Z",
          "cvrNummer": 35250824,
          "dokumenter": [
            {
              "dokumentType": "AARSRAPPORT",
              "dokumentMimeType": "application/pdf",
              "dokumentUrl": "http://regnskaber.virk.dk/42805253/ZG9rdW1lbnRsYWdlcjovLzAzLzUzLzFiLzAwLzdmLzI1OGYtNGU1Zi1iNWI3LThhZTIxMGZmMjZiOQ.pdf"
            },
            {
              "dokumentType": "AARSRAPPORT",
              "dokumentMimeType": "application/xml",
              "dokumentUrl": "http://regnskaber.virk.dk/42805253/ZG9rdW1lbnRsYWdlcjovLzAzL2JjL2ZkLzNiL2NmL2VhOTgtNGQ1OS04NGMyLTFlNjM2NzZiN2IzYQ.xml"
            }
          ],
          "regNummer": null,
          "indlaesningsTidspunkt": "2018-03-29T10:50:19.849Z",
          "offentliggoerelsesTidspunkt": "2016-06-17T14:14:20.371Z",
          "omgoerelse": false,
          "offentliggoerelsestype": "regnskab"
        }
      },
      {
        "_index": "indberetninger-20180424",
        "_type": "_doc",
        "_id": "urn:ofk:oid:15009067",
        "_score": 1,
        "_source": {
          "indlaesningsId": null,
          "sagsNummer": "14-172.478",
          "regnskab": {
            "regnskabsperiode": {
              "slutDato": "2013-12-31",
              "startDato": "2013-05-30"
            }
          },
          "sidstOpdateret": "2014-06-27T22:00:00.000Z",
          "cvrNummer": 35250824,
          "dokumenter": [
            {
              "dokumentType": "AARSRAPPORT",
              "dokumentMimeType": "application/pdf",
              "dokumentUrl": "http://regnskaber.virk.dk/42805253/Y3ZyLmRrOi8vcGRmcy8zNTI1MDgyNDtBcFM1MzAzNzM7MjAxMzA1MzA7MjAxMzEyMzE7UjtS.pdf"
            },
            {
              "dokumentType": "AARSRAPPORT",
              "dokumentMimeType": "application/xml",
              "dokumentUrl": "http://regnskaber.virk.dk/42805253/Y3ZyLmRrOi8veGJybHMvWC1GMTk3NEU2OS0yMDE0MDYyN18wODM3MDBfODc4.xml"
            }
          ],
          "regNummer": null,
          "indlaesningsTidspunkt": "2018-04-01T11:15:19.573Z",
          "offentliggoerelsesTidspunkt": "2014-06-27T22:00:00.000Z",
          "omgoerelse": false,
          "offentliggoerelsestype": "regnskab"
        }
      },
      {
        "_index": "indberetninger-20180424",
        "_type": "_doc",
        "_id": "urn:ofk:oid:5648114",
        "_score": 1,
        "_source": {
          "indlaesningsId": null,
          "sagsNummer": "X15-AF-06-PT",
          "regnskab": {
            "regnskabsperiode": {
              "slutDato": "2014-12-31",
              "startDato": "2014-01-01"
            }
          },
          "sidstOpdateret": "2015-07-03T13:23:44.006Z",
          "cvrNummer": 35250824,
          "dokumenter": [
            {
              "dokumentType": "AARSRAPPORT",
              "dokumentMimeType": "application/xml",
              "dokumentUrl": "http://regnskaber.virk.dk/42805253/ZG9rdW1lbnRsYWdlcjovLzAzL2Y3LzFjLzA3L2UyL2VmYWItNDJlYi1hYTk1LTg5NTQ0MjU3YWE1Nw.xml"
            },
            {
              "dokumentType": "AARSRAPPORT",
              "dokumentMimeType": "application/pdf",
              "dokumentUrl": "http://regnskaber.virk.dk/42805253/ZG9rdW1lbnRsYWdlcjovLzAzL2Y5L2FiL2NjL2ZiL2VkZjEtNGE2Yy1iOWI5LTY3ZTc3MTQxNDI1MQ.pdf"
            }
          ],
          "regNummer": null,
          "indlaesningsTidspunkt": "2018-03-30T09:06:04.420Z",
          "offentliggoerelsesTidspunkt": "2015-07-03T13:23:43.970Z",
          "omgoerelse": false,
          "offentliggoerelsestype": "regnskab"
        }
      },
      {
        "_index": "indberetninger-20180424",
        "_type": "_doc",
        "_id": "urn:ofk:oid:25874190",
        "_score": 1,
        "_source": {
          "cvrNummer": 35250824,
          "regNummer": null,
          "omgoerelse": false,
          "sagsNummer": "X18-AR-58-TZ",
          "offentliggoerelsestype": "regnskab",
          "regnskab": {
            "regnskabsperiode": {
              "startDato": "2017-01-01",
              "slutDato": "2017-12-31"
            }
          },
          "offentliggoerelsesTidspunkt": "2018-06-19T14:32:27.453Z",
          "indlaesningsTidspunkt": "2018-06-19T14:33:15.965Z",
          "sidstOpdateret": "2018-06-19T14:32:27.736Z",
          "dokumenter": [
            {
              "dokumentUrl": "http://regnskaber.virk.dk/42805253/ZG9rdW1lbnRsYWdlcjovLzAzLzMzL2E2L2NkL2Y4L2UzM2EtNDYxYS1iYzhjLTU4MzY4NDUxODk2Zg.xml",
              "dokumentMimeType": "application/xml",
              "dokumentType": "AARSRAPPORT"
            },
            {
              "dokumentUrl": "http://regnskaber.virk.dk/42805253/ZG9rdW1lbnRsYWdlcjovLzAzLzE3LzdjL2Q1Lzk1L2QzZWUtNDUxMy1hMjNmLWJjYjNhMDQyOGJmNQ.pdf",
              "dokumentMimeType": "application/pdf",
              "dokumentType": "AARSRAPPORT"
            }
          ],
          "indlaesningsId": "AWQYdha-0wkEsASkt5oe"
        }
      }
    ]
  }
}
