{
  "took": 3,
  "timed_out": false,
  "_shards": {
    "total": 3,
    "successful": 3,
    "skipped": 0,
    "failed": 0
  },
  "hits": {
    "total": 3,
    "max_score": 1,
    "hits": [
      {
        "_index": "indberetninger-20180424",
        "_type": "_doc",
        "_id": "urn:ofk:oid:22395316",
        "_score": 1,
        "_source": {
          "indlaesningsId": null,
          "sagsNummer": "X16-AW-27-WE",
          "regnskab": {
            "regnskabsperiode": {
              "slutDato": "2016-03-31",
              "startDato": "2015-04-01"
            }
          },
          "sidstOpdateret": "2016-05-19T21:30:42.595Z",
          "cvrNummer": 35802134,
          "dokumenter": [
            {
              "dokumentType": "AARSRAPPORT",
              "dokumentMimeType": "application/pdf",
              "dokumentUrl": "http://regnskaber.virk.dk/43120853/ZG9rdW1lbnRsYWdlcjovLzAzLzk3LzExLzYyL2FhLzE3OTUtNDk5Mi1hZWFkLTMxMzJiNTBiYjdiZA.pdf"
            },
            {
              "dokumentType": "AARSRAPPORT",
              "dokumentMimeType": "application/xhtml+xml",
              "dokumentUrl": "http://regnskaber.virk.dk/43120853/ZG9rdW1lbnRsYWdlcjovLzAzL2U1L2IxLzdmL2Y2L2YyY2QtNGRjNS05YjQ3LTYwMWViNzI3NTQ3MA.xhtml"
            },
            {
              "dokumentType": "AARSRAPPORT",
              "dokumentMimeType": "application/xml",
              "dokumentUrl": "http://regnskaber.virk.dk/43120853/ZG9rdW1lbnRsYWdlcjovLzAzL2IzL2YxLzJlLzQzLzMyMjMtNGUwMS1hYmY0LTFmY2M4ZGYyYjFlNg.xml"
            }
          ],
          "regNummer": null,
          "indlaesningsTidspunkt": "2018-03-28T22:37:21.675Z",
          "offentliggoerelsesTidspunkt": "2016-05-19T21:30:42.467Z",
          "omgoerelse": false,
          "offentliggoerelsestype": "regnskab"
        }
      },
      {
        "_index": "indberetninger-20180424",
        "_type": "_doc",
        "_id": "urn:ofk:oid:24509146",
        "_score": 1,
        "_source": {
          "indlaesningsId": null,
          "sagsNummer": "X17-AV-22-LY",
          "regnskab": {
            "regnskabsperiode": {
              "slutDato": "2017-03-31",
              "startDato": "2016-04-01"
            }
          },
          "sidstOpdateret": "2017-09-18T19:45:45.491Z",
          "cvrNummer": 35802134,
          "dokumenter": [
            {
              "dokumentType": "AARSRAPPORT",
              "dokumentMimeType": "application/pdf",
              "dokumentUrl": "http://regnskaber.virk.dk/43120853/ZG9rdW1lbnRsYWdlcjovLzAzLzU4L2RjL2E3L2E0L2RlYTQtNDhkNC1iOWIwLTI2YTIwZmRjZTE4OQ.pdf"
            },
            {
              "dokumentType": "AARSRAPPORT",
              "dokumentMimeType": "application/xhtml+xml",
              "dokumentUrl": "http://regnskaber.virk.dk/43120853/ZG9rdW1lbnRsYWdlcjovLzAzLzljLzgwLzYyLzM1LzlkYjEtNDljZS1iOTg1LThhZmE3OTI4ZDE3Ng.xhtml"
            },
            {
              "dokumentType": "AARSRAPPORT",
              "dokumentMimeType": "application/xml",
              "dokumentUrl": "http://regnskaber.virk.dk/43120853/ZG9rdW1lbnRsYWdlcjovLzAzL2U1LzQ4LzgxL2Y0LzM4OGYtNDExYy1hMDkzLWQxMjI5NjZhMzRhNA.xml"
            }
          ],
          "regNummer": null,
          "indlaesningsTidspunkt": "2018-03-27T15:58:19.408Z",
          "offentliggoerelsesTidspunkt": "2017-09-18T19:45:45.343Z",
          "omgoerelse": false,
          "offentliggoerelsestype": "regnskab"
        }
      },
      {
        "_index": "indberetninger-20180424",
        "_type": "_doc",
        "_id": "urn:ofk:oid:5290062",
        "_score": 1,
        "_source": {
          "indlaesningsId": null,
          "sagsNummer": "X15-AC-12-BQ",
          "regnskab": {
            "regnskabsperiode": {
              "slutDato": "2015-03-31",
              "startDato": "2014-03-10"
            }
          },
          "sidstOpdateret": "2015-05-22T18:48:01.827Z",
          "cvrNummer": 35802134,
          "dokumenter": [
            {
              "dokumentType": "AARSRAPPORT",
              "dokumentMimeType": "application/pdf",
              "dokumentUrl": "http://regnskaber.virk.dk/43120853/ZG9rdW1lbnRsYWdlcjovLzAzLzI0LzEzLzg4LzJjLzVhYjUtNGNjMC1iMmQ1LTEwN2JkYzFiMmNhMA.pdf"
            },
            {
              "dokumentType": "AARSRAPPORT",
              "dokumentMimeType": "application/xml",
              "dokumentUrl": "http://regnskaber.virk.dk/43120853/ZG9rdW1lbnRsYWdlcjovLzAzL2NmL2I2LzIzL2JjLzdhOTgtNGZjNi04NmY5LWNjMjMxMDk0YTQ5OQ.xml"
            },
            {
              "dokumentType": "AARSRAPPORT",
              "dokumentMimeType": "application/xhtml+xml",
              "dokumentUrl": "http://regnskaber.virk.dk/43120853/ZG9rdW1lbnRsYWdlcjovLzAzLzUxL2YyLzljLzhmLzk0MzYtNDE1MC04MzM2LTZhOGJmMmQ2OWExMA.xhtml"
            }
          ],
          "regNummer": null,
          "indlaesningsTidspunkt": "2018-03-30T15:17:38.148Z",
          "offentliggoerelsesTidspunkt": "2015-05-22T18:48:01.783Z",
          "omgoerelse": false,
          "offentliggoerelsestype": "regnskab"
        }
      }
    ]
  }
}
