{
  "took": 2,
  "timed_out": false,
  "_shards": {
    "total": 3,
    "successful": 3,
    "skipped": 0,
    "failed": 0
  },
  "hits": {
    "total": 1,
    "max_score": 1,
    "hits": [
      {
        "_index": "indberetninger-20180424",
        "_type": "_doc",
        "_id": "urn:ofk:oid:25607374",
        "_score": 1,
        "_source": {
          "cvrNummer": 38264281,
          "regNummer": null,
          "omgoerelse": false,
          "sagsNummer": "X18-AN-19-JU",
          "offentliggoerelsestype": "regnskab",
          "regnskab": {
            "regnskabsperiode": {
              "startDato": "2016-12-14",
              "slutDato": "2017-12-31"
            }
          },
          "offentliggoerelsesTidspunkt": "2018-05-30T11:44:51.917Z",
          "indlaesningsTidspunkt": "2018-05-30T11:45:57.275Z",
          "sidstOpdateret": "2018-05-30T11:44:52.076Z",
          "dokumenter": [
            {
              "dokumentUrl": "http://regnskaber.virk.dk/18246283/ZG9rdW1lbnRsYWdlcjovLzAzL2MwLzVmL2M4L2M5LzhiMjMtNGIzZC04ZmFmLTY4ZmY5ZDRjMGU1MQ.pdf",
              "dokumentMimeType": "application/pdf",
              "dokumentType": "AARSRAPPORT"
            },
            {
              "dokumentUrl": "http://regnskaber.virk.dk/18246283/ZG9rdW1lbnRsYWdlcjovLzAzL2U3LzE0LzI3L2NhLzc5OGItNDZlYi05MTRiLWM2NjZkZDQwOGRlNA.xml",
              "dokumentMimeType": "application/xml",
              "dokumentType": "AARSRAPPORT"
            }
          ],
          "indlaesningsId": "AWOw3Xk00wkEsASktLVc"
        }
      }
    ]
  }
}
